uchu/__init__.py
uchu/aws/__init__.py
uchu/aws/athena.py
uchu/aws/s3.py
uchu/do/__init__.py
uchu/do/space.py
uchu-0.0.12.dist-info/LICENSE
uchu-0.0.12.dist-info/METADATA
uchu-0.0.12.dist-info/WHEEL
uchu-0.0.12.dist-info/top_level.txt
uchu-0.0.12.dist-info/RECORD
